Metadata-Version: 1.0
Name: Distribution-Gauss-Bin
Version: 0.2
Summary: Gaussian and Binomial distributions
Home-page: UNKNOWN
Author: Nimish Soni
Author-email: nimish.soni@gmail.com
License: UNKNOWN
Platform: UNKNOWN
